resipe_scrapper_WWW.py
resipe_scrapper_www-0.0.1.dist-info/licenses/LICENSE.txt
resipe_scrapper_www-0.0.1.dist-info/METADATA
resipe_scrapper_www-0.0.1.dist-info/WHEEL
resipe_scrapper_www-0.0.1.dist-info/top_level.txt
resipe_scrapper_www-0.0.1.dist-info/RECORD
