Metadata-Version: 2.4
Name: resipe_scrapper_WWW
Version: 0.0.1
Summary: Scrapper for WWW
Author-email: hacker228 <leogamingrobloxlol@gmail.com>
License: MIT License
Classifier: Programming Language :: Python :: 3
Classifier: Operating System :: OS Independent
Requires-Python: >=3.10
License-File: LICENSE.txt
Requires-Dist: beautifulsoup>=4.12.3
Requires-Dist: pandas>=2.2.3
Requires-Dist: requests>=2.32.3
Dynamic: license-file
